jac_super/__init__.py
jac_super/plugin/console.jac
jac_super/plugin/impl/console.impl.jac
jac_super-0.1.0.dist-info/METADATA
jac_super-0.1.0.dist-info/WHEEL
jac_super-0.1.0.dist-info/entry_points.txt
jac_super-0.1.0.dist-info/top_level.txt
jac_super-0.1.0.dist-info/RECORD
