Metadata-Version: 2.4
Name: jac-super
Version: 0.1.0
Summary: Enhanced console output for Jac CLI with Rich formatting
Author-email: Jason Mars <jason@mars.ninja>
Maintainer-email: Jason Mars <jason@mars.ninja>
License-Expression: MIT
Project-URL: Repository, https://github.com/Jaseci-Labs/jaseci
Project-URL: Homepage, https://jaseci.org
Project-URL: Documentation, https://jac-lang.org
Keywords: jac,jaclang,jaseci,console,rich,cli
Requires-Python: >=3.12
Requires-Dist: jaclang>=0.9.9
Requires-Dist: rich>=13.0.0
